{"dependencies":[{"version":"1.0.0","assetId":"error-responses-trait","groupId":"e23e734a-7f55-4852-8d8d-fb70ad146ecd","provided":false}],"version":"1.0.0","originalFormatVersion":"1.0","apiVersion":"v1","descriptorVersion":"1.0.0","classifier":"raml-fragment","main":"collection-resource-type.raml","assetId":"collection-resource-type","groupId":"e23e734a-7f55-4852-8d8d-fb70ad146ecd","organizationId":"e23e734a-7f55-4852-8d8d-fb70ad146ecd","name":"Collection Resource Type","tags":[],"metadata":{"projectId":"1169d61a-c12f-4c43-bddf-3f5f42560452","branchId":"master","commitId":"b467d8b6d404ca8a97afe9a2516a05b27c6ed667"}}